falcon_redis_cache/__init__.py
falcon_redis_cache/hooks.py
falcon_redis_cache/middleware.py
falcon_redis_cache/resource.py
falcon_redis_cache-0.0.1.dist-info/DESCRIPTION.rst
falcon_redis_cache-0.0.1.dist-info/METADATA
falcon_redis_cache-0.0.1.dist-info/RECORD
falcon_redis_cache-0.0.1.dist-info/WHEEL
falcon_redis_cache-0.0.1.dist-info/metadata.json
falcon_redis_cache-0.0.1.dist-info/top_level.txt
